cgpa/__init__.py
cgpa/module.py
rollno/__init__.py
rollno/module.py
panimalar-1.0.1.dist-info/LICENSE
panimalar-1.0.1.dist-info/METADATA
panimalar-1.0.1.dist-info/WHEEL
panimalar-1.0.1.dist-info/top_level.txt
panimalar-1.0.1.dist-info/RECORD
