Metadata-Version: 2.1
Name: panimalar
Version: 1.0.1
Summary: A package of function created by and for The Coding Society, Panimalar Engineering College
Author-email: "aviiciii (Laaveshwaran Parthiban)" <laavesh1@gmail.com>, The Coding Society <codingsociety@psdc.org.in>
Project-URL: Homepage, https://github.com/thecoding-society/package
Project-URL: Bug Tracker, https://github.com/thecoding-society/package/issues
Classifier: Programming Language :: Python :: 3
Classifier: License :: OSI Approved :: MIT License
Classifier: Operating System :: OS Independent
Requires-Python: >=3.7
License-File: LICENSE
Requires-Dist: regex >=2022.10.31
Requires-Dist: pytest >=7.2.2
Requires-Dist: texttable >=1.6.4
